{"hafsa":{"username":"hafsa","bestSingleScore":0,"bestSingleTimeMillis":9223372036854775807,"bestSequentialScore":19,"bestSequentialTimeMillis":27015},"azerty":{"username":"azerty","bestSingleScore":5,"bestSingleTimeMillis":5820,"bestSequentialScore":0,"bestSequentialTimeMillis":9223372036854775807},"azertyy":{"username":"azertyy","bestSingleScore":5,"bestSingleTimeMillis":6438,"bestSequentialScore":0,"bestSequentialTimeMillis":9223372036854775807},"saliha":{"username":"saliha","bestSingleScore":5,"bestSingleTimeMillis":10269,"bestSequentialScore":0,"bestSequentialTimeMillis":9223372036854775807},"azertyyy":{"username":"azertyyy","bestSingleScore":7,"bestSingleTimeMillis":8545,"bestSequentialScore":0,"bestSequentialTimeMillis":9223372036854775807},"person":{"username":"person","bestSingleScore":5,"bestSingleTimeMillis":7324,"bestSequentialScore":0,"bestSequentialTimeMillis":9223372036854775807},"player":{"username":"player","bestSingleScore":5,"bestSingleTimeMillis":94367,"bestSequentialScore":0,"bestSequentialTimeMillis":9223372036854775807}}